LICENSE
README.md
pyproject.toml
src/tfr_reader/__init__.py
src/tfr_reader/indexer.py
src/tfr_reader/logging.py
src/tfr_reader/reader.py
src/tfr_reader.egg-info/PKG-INFO
src/tfr_reader.egg-info/SOURCES.txt
src/tfr_reader.egg-info/dependency_links.txt
src/tfr_reader.egg-info/requires.txt
src/tfr_reader.egg-info/top_level.txt
src/tfr_reader/cython/__init__.py
src/tfr_reader/cython/decoder.pyx
src/tfr_reader/cython/indexer.pyx
src/tfr_reader/example/__init__.py
src/tfr_reader/example/feature.py
src/tfr_reader/example/tfr_example_pb2.py
src/tfr_reader/filesystem/__init__.py
src/tfr_reader/filesystem/base.py
src/tfr_reader/filesystem/gcs.py
src/tfr_reader/filesystem/local.py
tests/test_indexer.py
tests/test_reader.py