Metadata-Version: 2.4
Name: tfr_reader
Version: 0.4.0
Summary: Tensorflow Record Reader with Random Access
Author: Krzysztof Kolasinski
License-Expression: MIT
Project-URL: Repository, https://github.com/kmkolasinski/tfrecords-reader
Keywords: dataframe,arrow,out-of-core
Classifier: Environment :: Console
Classifier: Intended Audience :: Science/Research
Classifier: Programming Language :: Python
Classifier: Programming Language :: Python :: 3 :: Only
Classifier: Programming Language :: Python :: 3.11
Classifier: Topic :: Scientific/Engineering
License-File: LICENSE
Requires-Dist: polars~=1.26
Requires-Dist: tqdm
Provides-Extra: google
Requires-Dist: gcsfs~=2025.3; extra == "google"
Requires-Dist: fsspec~=2025.3; extra == "google"
Requires-Dist: diskcache~=5.6; extra == "google"
Provides-Extra: dev
Requires-Dist: coverage; extra == "dev"
Requires-Dist: mypy; extra == "dev"
Requires-Dist: ruff; extra == "dev"
Requires-Dist: pytest~=7.2; extra == "dev"
Requires-Dist: pytest-cov~=4.0; extra == "dev"
Requires-Dist: pytest-sugar~=0.9; extra == "dev"
Requires-Dist: pytest-watch~=4.2.0; extra == "dev"
Requires-Dist: pytest-mock; extra == "dev"
Requires-Dist: numpy; extra == "dev"
Requires-Dist: Pillow; extra == "dev"
Requires-Dist: protobuf; extra == "dev"
Dynamic: license-file
